comocma/__init__.py
comocma/__main__.py
comocma/como.py
comocma/como_logger.py
comocma/hv.py
comocma/nondominatedarchive.py
comocma/sofomore_logger.py
comocma/test.py
comocma-0.6.0.dist-info/licenses/LICENSE
comocma-0.6.0.dist-info/METADATA
comocma-0.6.0.dist-info/WHEEL
comocma-0.6.0.dist-info/top_level.txt
comocma-0.6.0.dist-info/RECORD
