Metadata-Version: 2.4
Name: comocma
Version: 0.6.0
Summary: COMO-CMA-ES is the multiobjective Sofomore framework instantiated with the single-objective solver CMA-ES
Author: Cheikh Toure, Nikolaus Hansen, Eugenie Marescaux
Maintainer-email: Nikolaus Hansen <authors_firstname.lastname@inria.fr>
License-Expression: BSD-3-Clause
Project-URL: Homepage, https://github.com/CMA-ES/pycma
Project-URL: Repository, https://github.com/CMA-ES/pycma.git
Project-URL: Bug Tracker, https://github.com/CMA-ES/pycma/issues
Keywords: optimization,COMO-CMA-ES,Sofomore,multi-objective,CMA-ES,cmaes,evolution strategy
Classifier: Environment :: Console
Classifier: Framework :: IPython
Classifier: Framework :: Jupyter
Classifier: Intended Audience :: Science/Research
Classifier: Intended Audience :: Education
Classifier: Intended Audience :: Other Audience
Classifier: Topic :: Scientific/Engineering
Classifier: Topic :: Scientific/Engineering :: Mathematics
Classifier: Topic :: Scientific/Engineering :: Artificial Intelligence
Classifier: Operating System :: OS Independent
Classifier: Programming Language :: Python :: 2.7
Classifier: Programming Language :: Python :: 3
Classifier: Development Status :: 4 - Beta
License-File: LICENSE
Requires-Dist: numpy
Requires-Dist: cma>=3
Requires-Dist: moarchiving
Provides-Extra: plotting
Requires-Dist: matplotlib; extra == "plotting"
Provides-Extra: constrained-solution-tracking
Requires-Dist: moarchiving; extra == "constrained-solution-tracking"
Dynamic: license-file
